{
  "Young_Goblin": {
    "name": "어린 고블린",
    "level": 1,
    "hp": 80,
    "strength": 30,
    "agility": 3,
    "intelligence": 1,
    "defence": 5,
    "magicResistance": 0,
    "skills": [
      "SK_NormalAttack"
    ],
    "loottable": [ "equip_armor_chest_01", "consume_hp_potion_01", "consume_mp_potion_01" ]
  },
  "Fanged_Spider": {
    "name": "독니 거미",
    "level": 2,
    "hp": 120,
    "strength": 40,
    "agility": 5,
    "intelligence": 30,
    "defence": 0,
    "magicResistance": 0,
    "skills": [
      "SK_NormalAttack",
      "SK_PoisonCloud"
    ],
    "loottable": [ "consume_mp_potion_01", "consume_hp_potion_01", "consume_mp_potion_01" ]
  },
  "Prairie_Wolf": {
    "name": "초원 늑대",
    "level": 3,
    "hp": 160,
    "strength": 30,
    "agility": 7,
    "intelligence": 1,
    "defence": 0,
    "magicResistance": 0,
    "skills": [
      "SK_NormalAttack",
      "SK_TripleSlash"
    ],
    "loottable": [ "consume_mp_potion_01", "consume_hp_potion_01", "equip_weapon_sword_01", "equip_armor_chest_01", "consume_mp_potion_01" ]
  },
  "Orc_Warrior": {
    "name": "오크 전사",
    "level": 5,
    "hp": 300,
    "strength": 50,
    "agility": 8,
    "intelligence": 4,
    "defence": 10,
    "magicResistance": 0,
    "skills": [
      "SK_NormalAttack",
      "SK_StrengthBuff",
      "SK_TripleSlash"
    ],
    "loottable": [ "equip_weapon_axe_01" ]
  },
  "Forest_Rogue": {
    "name": "숲의 부랑자",
    "level": 6,
    "hp": 360,
    "strength": 60,
    "agility": 9,
    "intelligence": 60,
    "defence": 0,
    "magicResistance": 1,
    "skills": [
      "SK_NormalAttack",
      "SK_Heal",
      "SK_StrengthBuff"
    ],
    "loottable": [ "consume_mp_potion_01", "consume_hp_potion_01", "equip_weapon_axe_01" ]
  },
  "Hound_Pack_Leader": {
    "name": "사냥개 무리 우두머리",
    "level": 5,
    "hp": 320,
    "strength": 60,
    "agility": 12,
    "intelligence": 2,
    "defence": 0,
    "magicResistance": 0,
    "skills": [
      "SK_NormalAttack",
      "SK_TripleSlash"
    ],
    "loottable": [ "consume_mp_potion_01", "consume_hp_potion_01", "equip_weapon_axe_01", "equip_armor_chest_01", "equip_armor_robe_01" ]
  },
  "Venom_Assassin": {
    "name": "맹독 암살자",
    "level": 7,
    "hp": 420,
    "strength": 80,
    "agility": 18,
    "intelligence": 100,
    "defence": 10,
    "magicResistance": 4,
    "skills": [
      "SK_StrengthBuff",
      "SK_PoisonCloud"
    ],
    "loottable": [ "equip_thief_robe_01" ]
  },
  "Stonehide_Dwarf": {
    "name": "돌껍질 드워프",
    "level": 8,
    "hp": 400,
    "strength": 100,
    "agility": 5,
    "intelligence": 50,
    "defence": 30,
    "magicResistance": 0,
    "skills": [
      "SK_NormalAttack"
    ],
    "loottable": [ "consume_mp_potion_02", "consume_hp_potion_02", "equip_weapon_axe_01"]
  },
  "Thunder_Hawk": {
    "name": "번개 매",
    "level": 9,
    "hp": 300,
    "strength": 35,
    "agility": 25,
    "intelligence": 100,
    "defence": 0,
    "magicResistance": 20,
    "skills": [
      "SK_Heal",
      "SK_ArcaneBlast",
      "SK_Meditate"
    ],
    "loottable": [ "consume_mp_potion_02", "consume_hp_potion_02", "equip_thunderh's_orb_sword_01", "equip_accessory_ring_01"]
  },
  "Ironclad_Golem": {
    "name": "무쇠 갑옷 골렘",
    "level": 10,
    "hp": 500,
    "strength": 100,
    "agility": 7,
    "intelligence": 50,
    "defence": 50,
    "magicResistance": 0,
    "skills": [
      "SK_NormalAttack",
      "SK_Judgment"
    ],
    "loottable": [ "equip_armor_plate_01", "equip_paladin's_ring_01" ]
  },
  "Frail_Skeleton": {
    "name": "약골 스켈레톤",
    "level": 10,
    "hp": 440,
    "strength": 60,
    "agility": 4,
    "intelligence": 90,
    "defence": 20,
    "magicResistance": 1,
    "skills": [
      "SK_NormalAttack",
      "SK_PoisonCloud",
      "SK_Fireball"
    ],
    "loottable": [ "consume_mp_potion_02", "consume_hp_potion_02", "equip_skeleton's_ring_01", "equip_skeleton's_sword_01" ]
  },
  "Gloomy_Zombie": {
    "name": "음침한 좀비",
    "level": 10,
    "hp": 600,
    "strength": 90,
    "agility": 6,
    "intelligence": 90,
    "defence": 0,
    "magicResistance": 2,
    "skills": [
      "SK_TripleSlash",
      "SK_NormalAttack",
      "SK_PoisonCloud"
    ],
    "loottable": [ "consume_mp_potion_02", "consume_hp_potion_02", "equip_zombie's_plate_01", "equip_zombie's_ring_01"]
  },
  "Shadow_Wisplight": {
    "name": "어둠의 위스프",
    "level": 11,
    "hp": 100,
    "strength": 0,
    "agility": 7,
    "intelligence": 120,
    "defence": 999,
    "magicResistance": 10,
    "skills": [
      "SK_Meditate",
      "SK_ArcaneBlast",
      "SK_AbyssalCollapse"
    ],
    "loottable": [ "consume_mp_potion_02", "consume_hp_potion_02", "equip_wisplight's_plate_01", "equip_armor_robe_01"]
  },
  "Frozen_Specter": {
    "name": "얼어붙은 스펙터",
    "level": 12,
    "hp": 600,
    "strength": 120,
    "agility": 8,
    "intelligence": 120,
    "defence": 20,
    "magicResistance": 40,
    "skills": [
      "SK_PoisonCloud",
      "SK_Meditate",
      "SK_AbyssalCollapse",
      "SK_Fireball"
    ],
    "loottable": [ "equip_specter's_ring_01", "equip_Specter's_sword_01" ]
  },
  "Ancient_Dragon": {
    "name": "속박된 데스페라도",
    "level": 15,
    "hp": 1500,
    "strength": 60,
    "agility": 22,
    "intelligence": 60,
    "defence": 55,
    "magicResistance": 55,
    "skills": [
      "SK_ArcaneBlast",
      "SK_AbyssalCollapse",
      "SK_TripleSlash",
      "SK_Fireball"
    ]
  }
}